csp_nonce/__init__.py
csp_nonce/context_processors.py
csp_nonce/middleware.py
csp_nonce/utils.py
django_csp_nonce-1.0.0.dist-info/DESCRIPTION.rst
django_csp_nonce-1.0.0.dist-info/METADATA
django_csp_nonce-1.0.0.dist-info/RECORD
django_csp_nonce-1.0.0.dist-info/WHEEL
django_csp_nonce-1.0.0.dist-info/metadata.json
django_csp_nonce-1.0.0.dist-info/top_level.txt
tests/__init__.py
tests/settings.py
tests/test_context_processors.py
tests/test_django_csp_compatible.py
tests/test_middleware.py
tests/test_utils.py
