Metadata-Version: 2.0
Name: django-csp-nonce
Version: 1.0.0
Summary: Nonce support for Content Security Policy in Django.
Home-page: http://github.com/Bennyoak/django-csp-nonce
Author: Bennyoak
Author-email: benny@twosensedesign.com
License: MPL 2.0
Keywords: CSP Content Security Policy Nonce Django
Platform: UNKNOWN
Classifier: Development Status :: 5 - Production/Stable
Classifier: Environment :: Web Environment
Classifier: Programming Language :: Python
Classifier: License :: OSI Approved :: Mozilla Public License 2.0 (MPL 2.0)
Classifier: Operating System :: OS Independent
Classifier: Intended Audience :: Developers
Classifier: Topic :: Software Development :: Libraries :: Python Modules
Classifier: Programming Language :: Python
Classifier: Programming Language :: Python :: 2
Classifier: Programming Language :: Python :: 2.7
Classifier: Programming Language :: Python :: 3
Classifier: Programming Language :: Python :: 3.4
Classifier: Programming Language :: Python :: 3.5
Classifier: Programming Language :: Python :: Implementation :: CPython
Classifier: Framework :: Django
Requires-Dist: Django (>=1.6)
Provides-Extra: tests
Requires-Dist: django-csp; extra == 'tests'
Requires-Dist: mock (==1.0.1); extra == 'tests'
Requires-Dist: pep8 (==1.4.6); extra == 'tests'
Requires-Dist: pytest (==2.9.1); extra == 'tests'
Requires-Dist: pytest-django (==2.9.1); extra == 'tests'
Requires-Dist: pytest-flakes (==1.0.1); extra == 'tests'
Requires-Dist: pytest-pep8 (==1.0.6); extra == 'tests'
